augbuilder/__init__.py
augbuilder/additional_utils.py
augbuilder/aug_run.py
augbuilder/augmentation.json
augbuilder/augmentation.py
augbuilder/elements.py
augbuilder/layout.py
augbuilder/main.py
augbuilder/session_state.py
augbuilder/state_dict.py
augbuilder-0.0.3.data/data/config/augmentation.json
augbuilder-0.0.3.data/data/requirements/requirements.txt
augbuilder-0.0.3.dist-info/LICENSE
augbuilder-0.0.3.dist-info/METADATA
augbuilder-0.0.3.dist-info/WHEEL
augbuilder-0.0.3.dist-info/entry_points.txt
augbuilder-0.0.3.dist-info/top_level.txt
augbuilder-0.0.3.dist-info/RECORD
