Metadata-Version: 2.1
Name: augbuilder
Version: 0.0.3
Summary: A No-code solution to create the images transformation pipeline.
Home-page: UNKNOWN
Author: 7bits
Author-email: aloha@7bits.it
License: MIT
Project-URL: source, https://gitlab.7bits.it/internship-2020/ml-framework/augmentation-pipeline-builder
Project-URL: demo site, https://augbuilder.herokuapp.com/
Platform: UNKNOWN
Classifier: Development Status :: 3 - Alpha
Classifier: License :: OSI Approved :: MIT License
Classifier: Programming Language :: Python :: 3.6
Classifier: Programming Language :: Python :: 3.7
Classifier: Programming Language :: Python :: 3.8
Requires-Python: >=3.6
Requires-Dist: numpy (~=1.19.1)
Requires-Dist: albumentations (~=0.4.6)
Requires-Dist: streamlit (~=0.65.2)
